{
  "formats": {
    "title": "Támogatott fájlformátumok",
    "description": "A GroupDocs.Conversion for .NET a következő [fájlformátumokkal] (https://docs.groupdocs.com/conversion/net/supported-file-formats/) támogatja a műveleteket.",
    "groups": {
      "title_1": "Dokumentumformátumok",
      "title_2": "Képek és multimédia",
      "title_3": "Egyéb formátumok",
      "format_documents": "Dokumentumok",
      "format_images": "Képek",
      "format_diagram": "Diagram",
      "format_cad_gis": "CAD és GIS",
      "format_audio": "Hang",
      "format_video": "Videó",
      "format_vector_3d": "3D és vektor",
      "format_web": "Web",
      "format_archives": "Levéltár",
      "format_email_outlook": "E-mail és Outlook",
      "format_finance": "Pénzügy"
    }
  }
}