{
  "head": {
    "title": "{{ProgLang}} दस्तावेज़ रूपांतरण एपीआई | पीडीएफ, वर्ड, एक्सेल, पीपीटीएक्स, एचटीएमएल और छवियों को परिवर्तित करें",
    "description": "{{ProgLang}} दस्तावेज़ रूपांतरण एपीआई। पीडीएफ, वर्ड, डीओसी, डॉक्स, एक्सेल, स्प्रेडशीट, पीपीटी, पीपीटीएक्स, एचटीएमएल, पीएसडी, एमपीटी, एमपीपी, ईमेल, एमएसजी, ईएमएलएक्स, ऑटोकैड और छवि फ़ाइल प्रारूपों को परिवर्तित करें।"
  },
  "header": {
    "title_1": "दस्तावेज़ रूपांतरण",
    "title_2": "Node.js एपीआई के माध्यम से",
    "description": "पीडीएफ, माइक्रोसॉफ्ट ऑफिस, एचटीएमएल, ईबुक और छवि फ़ाइलों को परिवर्तित करने के लिए शक्तिशाली रूपांतरण एपीआई",
    "words": {
      "for": "के लिए"
    }
  },
  "actions": {
    "main": "निःशुल्क एनपीएम डाउनलोड",
    "alt": "लाइसेंसिंग",
    "title": "आरंभ करने के लिए तैयार हैं?",
    "description": "GroupDocs.Conversion सुविधाओं को निःशुल्क आज़माएँ या लाइसेंस का अनुरोध करें"
  },
  "release": {
    "title": "संस्करण {0} जारी किया गया",
    "notes": "देखें, क्या नया है",
    "downloads": "डाउनलोड"
  }
}